dsa_config/__init__.py
dsa_config/dsa_config.py
dsa_config/dsa_rest.py
dsa_config-1.5.dist-info/DESCRIPTION.rst
dsa_config-1.5.dist-info/METADATA
dsa_config-1.5.dist-info/RECORD
dsa_config-1.5.dist-info/WHEEL
dsa_config-1.5.dist-info/metadata.json
dsa_config-1.5.dist-info/top_level.txt
