Metadata-Version: 2.0
Name: dsa-config
Version: 1.5
Summary: DSC server configuration, DSC REST APIs
Home-page: UNKNOWN
Author: tqst_sit
Author-email: UNKNOWN
License: UNKNOWN
Platform: UNKNOWN
Requires-Dist: requests
Requires-Dist: tdtestpy
